vn_numberwords/__init__.py
vn_numberwords/cli.py
vn_numberwords/api/__init__.py
vn_numberwords/api/public.py
vn_numberwords/core/__init__.py
vn_numberwords/core/interfaces.py
vn_numberwords/core/transformer.py
vn_numberwords/core/utils.py
vn_numberwords/core/word_parser.py
vn_numberwords/dictionaries/__init__.py
vn_numberwords/dictionaries/base.py
vn_numberwords/dictionaries/south.py
vn_numberwords-0.2.0.dist-info/licenses/LICENSE
vn_numberwords-0.2.0.dist-info/METADATA
vn_numberwords-0.2.0.dist-info/WHEEL
vn_numberwords-0.2.0.dist-info/entry_points.txt
vn_numberwords-0.2.0.dist-info/top_level.txt
vn_numberwords-0.2.0.dist-info/RECORD
