Metadata-Version: 2.4
Name: vn-numberwords
Version: 0.2.0
Summary: Convert numbers to Vietnamese words and Vietnamese words to numbers (with North/South variants)
Author: Nguyen Huu Vuong
License: MIT
Project-URL: Homepage, https://github.com/rato-kaz/vn-numberwords
Project-URL: Repository, https://github.com/rato-kaz/vn-numberwords
Keywords: vietnamese,number to words,numberwords,currency,locale
Classifier: Programming Language :: Python :: 3
Classifier: License :: OSI Approved :: MIT License
Classifier: Operating System :: OS Independent
Classifier: Topic :: Text Processing :: Linguistic
Requires-Python: >=3.8
License-File: LICENSE
Provides-Extra: dev
Requires-Dist: pytest>=8.0; extra == "dev"
Requires-Dist: pre-commit>=3.5; extra == "dev"
Requires-Dist: mypy>=1.10; extra == "dev"
Requires-Dist: ruff>=0.6; extra == "dev"
Dynamic: license-file
